relaiss/__init__.py
relaiss/_version.py
relaiss/anomaly.py
relaiss/anomaly_config.py
relaiss/constants.py
relaiss/features.py
relaiss/fetch.py
relaiss/index.py
relaiss/plotting.py
relaiss/relaiss.py
relaiss/search.py
relaiss/utils.py
relaiss-1.2.3.dist-info/licenses/LICENSE
relaiss-1.2.3.dist-info/METADATA
relaiss-1.2.3.dist-info/WHEEL
relaiss-1.2.3.dist-info/top_level.txt
relaiss-1.2.3.dist-info/RECORD
