Metadata-Version: 2.4
Name: relaiss
Version: 1.2.3
Author: Evan Reynolds
Author-email: Alex Gagliano <gaglian2@mit.edu>, Ashley Villar <ashleyvillar@cfa.harvard.edu>
License: MIT License
Project-URL: Source Code, https://github.com/evan-reynolds/re-laiss/
Classifier: Development Status :: 4 - Beta
Classifier: License :: OSI Approved :: MIT License
Classifier: Intended Audience :: Developers
Classifier: Intended Audience :: Science/Research
Classifier: Operating System :: OS Independent
Classifier: Programming Language :: Python
Requires-Python: >=3.8
License-File: LICENSE
Requires-Dist: numpy
Requires-Dist: matplotlib
Requires-Dist: pandas
Requires-Dist: scipy
Requires-Dist: requests
Requires-Dist: sfdmap; python_version < "3.9"
Requires-Dist: sfdmap2; python_version >= "3.9"
Requires-Dist: matplotlib>=3.5
Requires-Dist: astropy>=5.0
Requires-Dist: annoy>=1.17
Requires-Dist: kneed
Requires-Dist: seaborn
Requires-Dist: statsmodels
Requires-Dist: scikit-learn>=1.3
Requires-Dist: gdown
Requires-Dist: pyod
Requires-Dist: corner
Requires-Dist: dust-extinction
Requires-Dist: astro-prost
Requires-Dist: absl-py<2
Requires-Dist: marshmallow<4
Requires-Dist: antares-client
Provides-Extra: dev
Requires-Dist: asv==0.6.4; extra == "dev"
Requires-Dist: jupyter; extra == "dev"
Requires-Dist: pre-commit; extra == "dev"
Requires-Dist: pytest; extra == "dev"
Requires-Dist: pytest-cov; extra == "dev"
Requires-Dist: ruff; extra == "dev"
Dynamic: license-file
